izitoast/__init__.py
izitoast/admin.py
izitoast/apps.py
izitoast/functions.py
izitoast/models.py
izitoast/tests.py
izitoast/urls.py
izitoast/views.py
izitoast/migrations/__init__.py
izitoast/static/iziToast.min.css
izitoast/static/iziToast.min.js
izitoast/static/jquery.min.js
izitoast/static/toastr.min.js
izitoast/templates/custom_response/diversify.txt
izitoast/templates/custom_response/mul-error-response.txt
izitoast/templates/custom_response/mul-info-response.txt
izitoast/templates/custom_response/mul-success-response.txt
izitoast/templates/custom_response/mul-warning-response.txt
izitoast/templates/includes/izitoast.html
izitoast-1.2.2.dist-info/LICENSE.rst
izitoast-1.2.2.dist-info/METADATA
izitoast-1.2.2.dist-info/WHEEL
izitoast-1.2.2.dist-info/top_level.txt
izitoast-1.2.2.dist-info/RECORD
