Metadata-Version: 2.1
Name: izitoast
Version: 1.2.2
Summary: Elegant, responsive, flexible, and lightweight notification plugin.
Home-page: https://djangoizitoast.pythonanywhere.com/
Author: Abdul Rahim K
Author-email: abdulrahim.uj@gmail.com
License: MIT
Keywords: izitoast
Classifier: Environment :: Web Environment
Classifier: Framework :: Django
Classifier: Intended Audience :: Developers
Classifier: License :: OSI Approved :: MIT License
Classifier: Operating System :: OS Independent
Classifier: Programming Language :: Python :: 3
Classifier: Topic :: Software Development :: Libraries :: Python Modules
License-File: LICENSE.rst
